local_ai/__init__.py
local_ai/__main__.py
local_ai/exceptions.py
local_ai/logging.py
local_ai/benchmark/__init__.py
local_ai/benchmark/agentic_runner.py
local_ai/benchmark/goose_runner.py
local_ai/benchmark/metrics.py
local_ai/benchmark/reporter.py
local_ai/benchmark/runner.py
local_ai/benchmark/schema.py
local_ai/benchmark/tasks.py
local_ai/benchmark/test_validator.py
local_ai/benchmark/recipes/todo_api_tdd.yaml
local_ai/benchmark/tasks/todo_api.toml
local_ai/benchmark/tasks/todo_api_tdd.toml
local_ai/cli/__init__.py
local_ai/cli/benchmark.py
local_ai/cli/config.py
local_ai/cli/main.py
local_ai/cli/models.py
local_ai/cli/server.py
local_ai/cli/status.py
local_ai/config/__init__.py
local_ai/config/loader.py
local_ai/config/schema.py
local_ai/hardware/__init__.py
local_ai/hardware/apple_silicon.py
local_ai/models/__init__.py
local_ai/models/huggingface.py
local_ai/models/recommender.py
local_ai/models/schema.py
local_ai/output/__init__.py
local_ai/output/console.py
local_ai/output/tables.py
local_ai/server/__init__.py
local_ai/server/__main__.py
local_ai/server/custom_server.py
local_ai/server/health.py
local_ai/server/manager.py
local_ai/server/welcome.py
local_ai/server/templates/welcome.html
local_ai_server-0.2.0a0.dist-info/METADATA
local_ai_server-0.2.0a0.dist-info/WHEEL
local_ai_server-0.2.0a0.dist-info/entry_points.txt
local_ai_server-0.2.0a0.dist-info/licenses/LICENSE.md
local_ai_server-0.2.0a0.dist-info/RECORD
