Metadata-Version: 2.4
Name: local-ai-server
Version: 0.2.0a0
Summary: Offline AI coding assistant for Apple Silicon. Run LLMs locally with OpenAI-compatible API.
Project-URL: Homepage, https://github.com/tumma72/local-ai
Project-URL: Repository, https://github.com/tumma72/local-ai
Project-URL: Issues, https://github.com/tumma72/local-ai/issues
License: Apache-2.0
License-File: LICENSE.md
Keywords: ai,apple-silicon,llm,local,mlx,offline,openai
Classifier: Development Status :: 3 - Alpha
Classifier: Intended Audience :: Developers
Classifier: License :: OSI Approved :: Apache Software License
Classifier: Operating System :: MacOS
Classifier: Programming Language :: Python :: 3.11
Classifier: Programming Language :: Python :: 3.12
Classifier: Programming Language :: Python :: 3.13
Classifier: Topic :: Scientific/Engineering :: Artificial Intelligence
Requires-Python: <3.14,>=3.11
Requires-Dist: httpx>=0.28.1
Requires-Dist: huggingface-hub>=0.28.0
Requires-Dist: loguru>=0.7.3
Requires-Dist: mlx-lm>=0.20.0
Requires-Dist: mlx-omni-server
Requires-Dist: openai>=2.11.0
Requires-Dist: psutil>=7.1.3
Requires-Dist: pydantic-settings[toml]>=2.12.0
Requires-Dist: pydantic>=2.12.5
Requires-Dist: rich>=14.2.0
Requires-Dist: tokenizers>=0.22.1
Requires-Dist: transformers>=4.57.3
Requires-Dist: typer>=0.20.0
